{
    "pokemons":[
        {
            "natDexNumber":197,
            "nickName":"Maia",
            "id":"LS1",
            "level":100
        },
        {
            "natDexNumber":248,
            "nickName":"Rod",
            "id":"LS2",
            "level":50
        },
        {
            "natDexNumber":302,
            "nickName":"",
            "id":"LS3",
            "level":80
        },
        {
            "natDexNumber":229,
            "nickName":"",
            "id":"LS4",
            "level":60
        }
    ],
    "moves":[
        {
            "pokemon":"LS1",
            "attack":"MT0100"
        },
        {
            "pokemon":"LS1",
            "attack":"MT0097"
        },
        {
            "pokemon":"LS1",
            "attack":"MT0106"
        },
        {
            "pokemon":"LS1",
            "attack":"MT0030"
        },
        {
            "pokemon":"LS2",
            "attack":"MT0095"
        },
        {
            "pokemon":"LS2",
            "attack":"MT0101"
        },
        {
            "pokemon":"LS2",
            "attack":"MT0102"
        },
        {
            "pokemon":"LS2",
            "attack":"MT0048"
        },
        {
            "pokemon":"LS3",
            "attack":"MT0107"
        },
        {
            "pokemon":"LS3",
            "attack":"MT0106"
        },
        {
            "pokemon":"LS3",
            "attack":"MT0030"
        },
        {
            "pokemon":"LS3",
            "attack":"MT0095"
        },
        {
            "pokemon":"LS4",
            "attack":"MT0108"
        },
        {
            "pokemon":"LS4",
            "attack":"MT0068"
        },
        {
            "pokemon":"LS4",
            "attack":"MT0038"
        },
        {
            "pokemon":"LS4",
            "attack":"MT0095"
        }
    ],
    "stats":[
        {
            "id":"LS1",
            "hp":394,
            "phyDamage":251,
            "phyDefense":350,
            "speDamage":240,
            "speDefense":394,
            "speed":251
        },
        {
            "id":"LS2",
            "hp":404,
            "phyDamage":403,
            "phyDefense":350,
            "speDamage":317,
            "speDefense":328,
            "speed":243
        },
        {
            "id":"LS3",
            "hp":250,
            "phyDamage":160,
            "phyDefense":160,
            "speDamage":140,
            "speDefense":141,
            "speed":180
        },
        {
            "id":"LS4",
            "hp":320,
            "phyDamage":290,
            "phyDefense":200,
            "speDamage":340,
            "speDefense":275,
            "speed":300
        }
    ]
}